fairshare/__init__.py
fairshare/core.py
fairshare/helpers.py
fairshare/patches.py
fairshare/serializers.py
fairshare/base/__init__.py
fairshare/base/messages.py
fairshare/base/serializers.py
fairshare-0.1.1.dist-info/LICENCE
fairshare-0.1.1.dist-info/METADATA
fairshare-0.1.1.dist-info/WHEEL
fairshare-0.1.1.dist-info/top_level.txt
fairshare-0.1.1.dist-info/RECORD
