Metadata-Version: 2.1
Name: fairshare
Version: 0.1.1
Summary: Simple fair queue implementation on Python
Author: Jerzy Kurowski
License: MIT
License-File: LICENCE
Requires-Dist: pydantic >=2.5.0
Requires-Dist: redis[hiredis] >=5.0.1
Provides-Extra: extra
Requires-Dist: ujson >=5.2.0 ; extra == 'extra'
Requires-Dist: xxhash >=3.0.0 ; extra == 'extra'
Requires-Dist: msgpack >=1.0.4 ; extra == 'extra'
